fdtdream/__init__.py
fdtdream/fdtdream.py
fdtdream/FDTDiscover/__init__.py
fdtdream/FDTDiscover/app_interface.py
fdtdream/FDTDiscover/application.py
fdtdream/FDTDiscover/shared.py
fdtdream/FDTDiscover/signal_busses.py
fdtdream/FDTDiscover/dbPanel/__init__.py
fdtdream/FDTDiscover/dbPanel/signals.py
fdtdream/FDTDiscover/dbPanel/controllers/__init__.py
fdtdream/FDTDiscover/dbPanel/controllers/databaseController.py
fdtdream/FDTDiscover/dbPanel/controllers/rightClickController.py
fdtdream/FDTDiscover/dbPanel/controllers/treeViewController.py
fdtdream/FDTDiscover/dbPanel/models/__init__.py
fdtdream/FDTDiscover/dbPanel/models/models.py
fdtdream/FDTDiscover/dbPanel/processes/__init__.py
fdtdream/FDTDiscover/dbPanel/processes/copyToDatabase.py
fdtdream/FDTDiscover/dbPanel/processes/parameterFetcher.py
fdtdream/FDTDiscover/dbPanel/processes/populateTree.py
fdtdream/FDTDiscover/dbPanel/widgets/__init__.py
fdtdream/FDTDiscover/dbPanel/widgets/changeCategoryDialog.py
fdtdream/FDTDiscover/dbPanel/widgets/databasePanel.py
fdtdream/FDTDiscover/dbPanel/widgets/editInfoDialog.py
fdtdream/FDTDiscover/dbPanel/widgets/editParametersDialog.py
fdtdream/FDTDiscover/dbPanel/widgets/infoButton.py
fdtdream/FDTDiscover/dbPanel/widgets/parameterTable.py
fdtdream/FDTDiscover/dbPanel/widgets/treeView.py
fdtdream/FDTDiscover/fieldPanel/__init__.py
fdtdream/FDTDiscover/fieldPanel/signals.py
fdtdream/FDTDiscover/fieldPanel/controllers/__init__.py
fdtdream/FDTDiscover/fieldPanel/controllers/plotController.py
fdtdream/FDTDiscover/fieldPanel/models/__init__.py
fdtdream/FDTDiscover/fieldPanel/processes/__init__.py
fdtdream/FDTDiscover/fieldPanel/widgets/__init__.py
fdtdream/FDTDiscover/fieldPanel/widgets/canvas.py
fdtdream/FDTDiscover/fieldPanel/widgets/fieldPanel.py
fdtdream/FDTDiscover/fieldPanel/widgets/settingsPanel.py
fdtdream/FDTDiscover/field_plot/__init__.py
fdtdream/FDTDiscover/field_plot/main.py
fdtdream/FDTDiscover/field_plot/controllers/__init__.py
fdtdream-0.2.12.dist-info/METADATA
fdtdream-0.2.12.dist-info/WHEEL
fdtdream-0.2.12.dist-info/licenses/LICENSE
fdtdream-0.2.12.dist-info/RECORD
